{
  "background": {
    "src": "/media/jp19060/Expansion/Cze/sci-fi/Asset_Packs_and_Resources/Nebulas_Slow3.webm"
  },
  "elements": [
    {
      "collapsed": false,
      "height": 1080,
      "hiddenProperties": [
        "x",
        "y",
        "width",
        "height"
      ],
      "id": "grid",
      "invisible": false,
      "locked": true,
      "opacity": 50,
      "rotation": 0,
      "src": "/home/jp19060/Github/DnD_Images/grid_27x15_1080p.png",
      "type": "image",
      "width": 1920,
      "x": 0,
      "y": 0
    }
  ],
  "screen": {
    "monitor": 1
  }
}